Metadata-Version: 2.1
Name: pytent
Version: 0.0.1
Summary: Package for collecting, processing and visualizing patent data for data science
Home-page: https://github.com/raulivan/pytent
Author: Raulivan Rodrigo da Silva
Author-email: raulivanrodrigo@gmail.com
License: MIT License
Keywords: pytent,patent,inpi,espacenet,data science
License-File: LICENSE
